[
  {
    "token": "45564b6b9933335bbd89944b84c810f6",
    "rater_label": "a",
    "clip_id": 1,
    "clip_filename": "",
    "watched_complete": true,
    "watch_progress_sec": 5.01551,
    "duration_sec": 5.01551,
    "memorability": null,
    "perceived_agency": null,
    "best_context": null,
    "payload": {
      "R_2": "1",
      "R_3": "2",
      "R_4": "1",
      "R_5": "1",
      "R_6": "1",
      "R_7": "1",
      "R_8": "1",
      "R_9": "1",
      "comments": "",
      "attention": "Mostly sound"
    },
    "end_notes": {},
    "updated_at": "2026-01-01T23:55:37.648428+00:00"
  },
  {
    "token": "fb2e62201e7bad22ec1868088c324770",
    "rater_label": "abc",
    "clip_id": 2,
    "clip_filename": "",
    "watched_complete": true,
    "watch_progress_sec": 66.316667,
    "duration_sec": 66.316667,
    "memorability": 2,
    "perceived_agency": 5,
    "best_context": "workshop_education",
    "payload": {
      "R_1": "1",
      "R_2": "1",
      "R_3": "1",
      "R_4": "1",
      "R_5": "1",
      "R_6": "1",
      "R_7": "1",
      "R_8": "1",
      "R_9": "1",
      "comments": "",
      "attention": "Balanced"
    },
    "end_notes": {
      "top1": "cant remember",
      "top2": "as",
      "top3": "1",
      "fusion_notes": ""
    },
    "updated_at": "2026-01-05T12:45:57.353425+00:00"
  },
  {
    "token": "fb2e62201e7bad22ec1868088c324770",
    "rater_label": "abc",
    "clip_id": 1,
    "clip_filename": "",
    "watched_complete": true,
    "watch_progress_sec": 5.01551,
    "duration_sec": 5.01551,
    "memorability": 4,
    "perceived_agency": 6,
    "best_context": "workshop_education",
    "payload": {
      "R_1": "1",
      "R_2": "1",
      "R_3": "1",
      "R_4": "1",
      "R_5": "1",
      "R_6": "1",
      "R_7": "1",
      "R_8": "1",
      "R_9": "1",
      "comments": "",
      "attention": "Mostly light"
    },
    "end_notes": {
      "top1": "cant remember",
      "top2": "as",
      "top3": "1",
      "fusion_notes": ""
    },
    "updated_at": "2026-01-05T12:46:26.939923+00:00"
  },
  {
    "token": "96038ee52ac3f2f4e55c9acf5d1a4b28",
    "rater_label": "test1",
    "clip_id": 3,
    "clip_filename": "",
    "watched_complete": true,
    "watch_progress_sec": 65.483333,
    "duration_sec": 65.483333,
    "memorability": 1,
    "perceived_agency": 1,
    "best_context": "installation_gallery",
    "payload": {
      "R_1": "1",
      "R_2": "1",
      "R_3": "1",
      "R_4": "1",
      "R_5": "1",
      "R_6": "1",
      "R_7": "1",
      "R_8": "1",
      "R_9": "1",
      "comments": "",
      "attention": "Balanced",
      "condition_guess": "audiovisual"
    },
    "end_notes": {},
    "updated_at": "2026-01-09T10:14:31.606410+00:00"
  },
  {
    "token": "96038ee52ac3f2f4e55c9acf5d1a4b28",
    "rater_label": "test1",
    "clip_id": 37,
    "clip_filename": "",
    "watched_complete": true,
    "watch_progress_sec": 82.433333,
    "duration_sec": 82.433333,
    "memorability": 7,
    "perceived_agency": 4,
    "best_context": null,
    "payload": {
      "R_1": "7",
      "R_2": "7",
      "R_3": "7",
      "R_4": "7",
      "R_5": "7",
      "R_6": "7",
      "R_7": "7",
      "R_8": "7",
      "R_9": "7",
      "comments": ""
    },
    "end_notes": {},
    "updated_at": "2026-01-09T10:23:46.288544+00:00"
  },
  {
    "token": "d8e1b047ebad142949de7c5c941a96db",
    "rater_label": "test3",
    "clip_id": 14,
    "clip_filename": "",
    "watched_complete": true,
    "watch_progress_sec": 135.95,
    "duration_sec": 135.95,
    "memorability": null,
    "perceived_agency": 5,
    "best_context": null,
    "payload": {
      "R_1": "7",
      "R_2": "3",
      "R_3": "4",
      "R_4": "5",
      "R_5": "6",
      "R_6": "4",
      "R_7": "2",
      "R_8": "6",
      "R_9": "4",
      "comments": ""
    },
    "end_notes": {},
    "updated_at": "2026-01-09T11:00:39.911544+00:00"
  },
  {
    "token": "0d88046d8223109f58dffe52ebc3070b",
    "rater_label": "test4",
    "clip_id": 26,
    "clip_filename": "",
    "watched_complete": true,
    "watch_progress_sec": 97.483333,
    "duration_sec": 97.483333,
    "memorability": null,
    "perceived_agency": 7,
    "best_context": "installation_gallery",
    "payload": {
      "R_1": "7",
      "R_2": "7",
      "R_3": "7",
      "R_4": "7",
      "R_5": "7",
      "R_6": "7",
      "R_7": "7",
      "R_8": "7",
      "R_9": "7",
      "comments": "",
      "attention": "Mostly sound",
      "condition_guess": "audio_only"
    },
    "end_notes": {},
    "updated_at": "2026-01-09T11:08:25.343782+00:00"
  },
  {
    "token": "0d88046d8223109f58dffe52ebc3070b",
    "rater_label": "test4",
    "clip_id": 54,
    "clip_filename": "",
    "watched_complete": true,
    "watch_progress_sec": 114.766667,
    "duration_sec": 114.766667,
    "memorability": null,
    "perceived_agency": 7,
    "best_context": "live_performance",
    "payload": {
      "R_1": "7",
      "R_2": "7",
      "R_3": "7",
      "R_4": "7",
      "R_5": "7",
      "R_6": "7",
      "R_7": "7",
      "R_8": "7",
      "R_9": "7",
      "comments": "",
      "attention": "Balanced",
      "condition_guess": "audiovisual"
    },
    "end_notes": {},
    "updated_at": "2026-01-09T11:10:51.701168+00:00"
  },
  {
    "token": "0d88046d8223109f58dffe52ebc3070b",
    "rater_label": "test4",
    "clip_id": 10,
    "clip_filename": "",
    "watched_complete": true,
    "watch_progress_sec": 76.516667,
    "duration_sec": 76.516667,
    "memorability": null,
    "perceived_agency": 7,
    "best_context": "live_performance",
    "payload": {
      "R_1": "7",
      "R_2": "7",
      "R_3": "7",
      "R_4": "7",
      "R_5": "7",
      "R_6": "7",
      "R_7": "7",
      "R_8": "7",
      "R_9": "7",
      "comments": "",
      "attention": "Mostly light",
      "condition_guess": "visual_only"
    },
    "end_notes": {},
    "updated_at": "2026-01-09T11:12:37.247391+00:00"
  },
  {
    "token": "0d88046d8223109f58dffe52ebc3070b",
    "rater_label": "test4",
    "clip_id": 15,
    "clip_filename": "",
    "watched_complete": true,
    "watch_progress_sec": 114.233333,
    "duration_sec": 114.233333,
    "memorability": null,
    "perceived_agency": 7,
    "best_context": "live_performance",
    "payload": {
      "R_1": "7",
      "R_2": "7",
      "R_3": "7",
      "R_4": "7",
      "R_5": "7",
      "R_6": "7",
      "R_7": "7",
      "R_8": "7",
      "R_9": "7",
      "comments": "",
      "attention": "Balanced",
      "condition_guess": "audiovisual"
    },
    "end_notes": {},
    "updated_at": "2026-01-09T11:14:57.128230+00:00"
  },
  {
    "token": "131535b09d356142ca96b1cf94d910f6",
    "rater_label": "test10",
    "clip_id": 72,
    "clip_filename": "",
    "watched_complete": true,
    "watch_progress_sec": 76.3,
    "duration_sec": 76.3,
    "memorability": null,
    "perceived_agency": 1,
    "best_context": "installation_gallery",
    "payload": {
      "R_1": "1",
      "R_2": "1",
      "R_3": "1",
      "R_4": "1",
      "R_5": "1",
      "R_6": "1",
      "R_7": "1",
      "R_8": "1",
      "R_9": "1",
      "comments": "",
      "attention": "Mostly light",
      "condition_guess": "audiovisual"
    },
    "end_notes": {},
    "updated_at": "2026-01-10T14:11:32.067640+00:00"
  },
  {
    "token": "419c8d1bd04068092aa2cc32c9cbb2fe",
    "rater_label": "test12",
    "clip_id": 62,
    "clip_filename": "1661J_A_2026-01-06_12-12-03.mp4",
    "watched_complete": true,
    "watch_progress_sec": 72.285026,
    "duration_sec": 72.285026,
    "memorability": null,
    "perceived_agency": 1,
    "best_context": "installation_gallery",
    "payload": {
      "R_1": "1",
      "R_2": "1",
      "R_3": "1",
      "R_4": "1",
      "R_5": "1",
      "R_6": "1",
      "R_7": "1",
      "R_8": "1",
      "R_9": "1",
      "comments": "",
      "attention": "Mostly sound"
    },
    "end_notes": {},
    "updated_at": "2026-01-10T14:24:17.245492+00:00"
  },
  {
    "token": "df4d436f727d82405252a9777921fba5",
    "rater_label": "test14",
    "clip_id": 62,
    "clip_filename": "1661J_A_2026-01-06_12-12-03.mp4",
    "watched_complete": true,
    "watch_progress_sec": 72.285026,
    "duration_sec": 72.285026,
    "memorability": null,
    "perceived_agency": 1,
    "best_context": "background_ambience",
    "payload": {
      "R_1": "1",
      "R_2": "1",
      "R_3": "1",
      "R_4": "1",
      "R_5": "1",
      "R_6": "1",
      "R_7": "1",
      "R_8": "1",
      "R_9": "1",
      "comments": "",
      "attention": "Balanced",
      "condition_guess": "audiovisual"
    },
    "end_notes": {
      "further_comments": "yay",
      "lowest_rated_notes": "bad",
      "highest_rated_notes": "great"
    },
    "updated_at": "2026-01-10T14:32:52.089653+00:00"
  },
  {
    "token": "89723ec33c35bf71095d84479570e0b0",
    "rater_label": "test16",
    "clip_id": 62,
    "clip_filename": "1661J_A_2026-01-06_12-12-03.mp4",
    "watched_complete": true,
    "watch_progress_sec": 72.285026,
    "duration_sec": 72.285026,
    "memorability": null,
    "perceived_agency": 1,
    "best_context": "unsure",
    "payload": {
      "R_1": "1",
      "R_2": "1",
      "R_3": "1",
      "R_4": "1",
      "R_5": "1",
      "R_6": "1",
      "R_7": "1",
      "R_8": "1",
      "R_9": "1",
      "comments": "",
      "attention": "It varied / unsure",
      "condition_guess": "unsure"
    },
    "end_notes": {
      "further_comments": "na",
      "lowest_rated_notes": "yes",
      "highest_rated_notes": "no"
    },
    "updated_at": "2026-01-10T14:41:09.952849+00:00"
  },
  {
    "token": "995592ee3e381c2b3a76c5c11117c350",
    "rater_label": "test16",
    "clip_id": 62,
    "clip_filename": "1661J_A_2026-01-06_12-12-03.mp4",
    "watched_complete": true,
    "watch_progress_sec": 72.285026,
    "duration_sec": 72.285026,
    "memorability": null,
    "perceived_agency": 1,
    "best_context": "workshop_education",
    "payload": {
      "R_1": "1",
      "R_2": "1",
      "R_3": "1",
      "R_4": "1",
      "R_5": "1",
      "R_6": "1",
      "R_7": "1",
      "R_8": "1",
      "R_9": "1",
      "comments": "",
      "attention": "Balanced",
      "condition_guess": "audiovisual"
    },
    "end_notes": {
      "further_comments": "hey?",
      "lowest_rated_notes": "yaaaay",
      "highest_rated_notes": "naaay"
    },
    "updated_at": "2026-01-10T14:49:41.352692+00:00"
  },
  {
    "token": "307c9d160a4ad17280358bb0d0ebb649",
    "rater_label": "test18",
    "clip_id": 108,
    "clip_filename": "5220H_C_2026-01-05_20-04-01.mp4",
    "watched_complete": true,
    "watch_progress_sec": 76.546029,
    "duration_sec": 76.566667,
    "memorability": null,
    "perceived_agency": 2,
    "best_context": null,
    "payload": {
      "R_1": "2",
      "R_2": "2",
      "R_3": "2",
      "R_4": "2",
      "R_5": "2",
      "R_6": "2",
      "R_7": "2",
      "R_8": "2",
      "R_9": "2",
      "comments": ""
    },
    "end_notes": {},
    "updated_at": "2026-01-10T14:59:41.123575+00:00"
  }
]